upip
upip_utarfile
