Metadata-Version: 1.2
Name: micropython-cpython-upip
Version: 0.3
Summary: MicroPython module upip ported to CPython
Home-page: https://github.com/pfalcon/micropython-lib
Author: Paul Sokolovsky
Author-email: micropython-lib@googlegroups.com
Maintainer: Paul Sokolovsky
Maintainer-email: micropython-lib@googlegroups.com
License: Python
Platform: UNKNOWN
